dammcheck-0.1.2.dist-info/METADATA
dammcheck-0.1.2.dist-info/WHEEL
dammcheck-0.1.2.dist-info/license_files/LICENSE
dammcheck/__init__.py
dammcheck/dammcheck.pypy39-pp73-s390x-linux-gnu.so
dammcheck-0.1.2.dist-info/RECORD
