Metadata-Version: 2.1
Name: dammcheck
Version: 0.1.2
Classifier: Programming Language :: Rust
Classifier: Programming Language :: Python :: Implementation :: CPython
Classifier: Programming Language :: Python :: Implementation :: PyPy
License-File: LICENSE
Summary: Implementation of the Damm Algorithm in various bases/alphabets
Author: Jesse Wallace
Requires-Python: >=3.7
Project-URL: Source Code, https://github.com/J-Wall/dammcheck
